pygments_cl_repl/__init__.py
pygments_cl_repl/test_pygments_cl_repl.py
pygments_cl_repl-0.2.2.dist-info/LICENSE
pygments_cl_repl-0.2.2.dist-info/METADATA
pygments_cl_repl-0.2.2.dist-info/WHEEL
pygments_cl_repl-0.2.2.dist-info/entry_points.txt
pygments_cl_repl-0.2.2.dist-info/top_level.txt
pygments_cl_repl-0.2.2.dist-info/RECORD
