Metadata-Version: 2.1
Name: pygments-cl-repl
Version: 0.2.2
Summary: Pygments lexer for Common Lisp REPL
Author-email: Russell Sim <rsl@simopolis.xyz>
License: GPL-3.0-or-later
Project-URL: Homepage, https://git.sr.ht/~rsl/pygments-cl-repl
Project-URL: Bug Reports, https://todo.sr.ht/~rsl/sphinxcontrib-cldomain
Project-URL: Source, https://git.sr.ht/~rsl/pygments-cl-repl
Classifier: Development Status :: 4 - Beta
Classifier: Environment :: Plugins
Classifier: Intended Audience :: Developers
Classifier: License :: OSI Approved :: GNU General Public License v3 or later (GPLv3+)
Classifier: Operating System :: OS Independent
Classifier: Programming Language :: Python
Classifier: Programming Language :: Python :: 3
Classifier: Topic :: Software Development :: Libraries :: Python Modules
Classifier: Framework :: Django
Classifier: Programming Language :: Python :: 3
Requires-Python: >=3.7
License-File: LICENSE
Requires-Dist: pygments
